lxd_tools/__init__.py
lxd_tools/cli.py
lxd_tools/constant.py
lxd_tools/py.typed
lxd_tools/resources.py
lxd_tools-0.5.0.dist-info/entry_points.txt
lxd_tools-0.5.0.dist-info/LICENSE.txt
lxd_tools-0.5.0.dist-info/WHEEL
lxd_tools-0.5.0.dist-info/METADATA
lxd_tools-0.5.0.dist-info/RECORD
